[
  {
    "clienteId": "cli_081",
    "clienteNombre": "MODATEXTIL DEL CARIBE S.A.S.",
    "clienteTelefono": "N/A",
    "vendedorNombre": "Usuario Soporte",
    "items": [
      {
        "id": "cart_1783451152327_cxb1",
        "prendaRef": "13300",
        "nombrePrenda": "CAMISETA COLOMBIA 10",
        "categoria": "Dama",
        "talla": "N/A",
        "tallasDetalle": {
          "N/A": 24
        },
        "novedad": "solo beigs",
        "cantidad": 24,
        "precioUnitario": 29900,
        "total": 717600
      }
    ],
    "subtotal": 717600,
    "porcentajeDescuento": 0,
    "montoDescuento": 0,
    "total": 717600,
    "estado": "Pendiente",
    "notas": "",
    "fechaEntregaEstimada": "2026-07-07",
    "fechaLimiteDespacho": "",
    "facturacionFE": 100,
    "facturacionRM": 0,
    "id": "ped_1783451175286",
    "numeroPedido": "SOP-001",
    "fecha": "2026-07-07",
    "campana": "Vacaciones 2026",
    "sincronizado": 1,
    "idLocal": 2
  },
  {
    "clienteId": "cli_270",
    "clienteNombre": "AL MUSTAKIM",
    "clienteTelefono": "N/A",
    "vendedorNombre": "Usuario Soporte",
    "items": [
      {
        "id": "cart_1783540658214_0rpf",
        "prendaRef": "13300",
        "nombrePrenda": "CAMISETA COLOMBIA 10",
        "categoria": "Dama",
        "talla": "S-8, M-8, L-6",
        "tallasDetalle": {
          "S": 8,
          "M": 8,
          "L": 6
        },
        "cantidad": 22,
        "precioUnitario": 29900,
        "total": 657800
      },
      {
        "id": "cart_1783540695831_i25z",
        "prendaRef": "13296",
        "nombrePrenda": "CAMISETA COLOMBIA",
        "categoria": "Dama",
        "talla": "N/A",
        "tallasDetalle": {
          "N/A": 24
        },
        "novedad": "solo amarilla",
        "cantidad": 24,
        "precioUnitario": 24900,
        "total": 597600
      },
      {
        "id": "cart_1783540735138_pxse",
        "prendaRef": "13282",
        "nombrePrenda": "BLUSON CRUZADO BOTONES",
        "categoria": "Dama",
        "talla": "N/A",
        "tallasDetalle": {
          "N/A": 22
        },
        "novedad": "recargar beigs",
        "cantidad": 22,
        "precioUnitario": 22900,
        "total": 503800
      }
    ],
    "subtotal": 1759200,
    "porcentajeDescuento": 0,
    "montoDescuento": 0,
    "total": 1759200,
    "estado": "Cancelado",
    "notas": "",
    "fechaEntregaEstimada": "2026-07-08",
    "fechaLimiteDespacho": "",
    "facturacionFE": 50,
    "facturacionRM": 50,
    "id": "ped_1783540747588",
    "numeroPedido": "SOP-003",
    "fecha": "2026-07-08",
    "campana": "Vacaciones 2026",
    "sincronizado": 1,
    "idLocal": 4,
    "fechaCancelado": "2026-07-09"
  },
  {
    "clienteId": "cli_173",
    "clienteNombre": "INVERSIONES LA MEDIA NARANJA S.A.S",
    "clienteTelefono": "N/A",
    "vendedorNombre": "Usuario Soporte",
    "items": [
      {
        "id": "cart_1783622155234_sx2y",
        "prendaRef": "13120",
        "nombrePrenda": "ESTRAPLE BOLERO",
        "categoria": "Dama",
        "talla": "N/A",
        "tallasDetalle": {
          "N/A": 6
        },
        "novedad": "No negro",
        "cantidad": 6,
        "precioUnitario": 17900,
        "total": 107400
      },
      {
        "id": "cart_1783622178892_l1hb",
        "prendaRef": "13042",
        "nombrePrenda": "BL MANG BOLE ARABEZC",
        "categoria": "Dama",
        "talla": "N/A",
        "tallasDetalle": {
          "N/A": 20
        },
        "cantidad": 20,
        "precioUnitario": 29900,
        "total": 598000
      }
    ],
    "subtotal": 705400,
    "porcentajeDescuento": 0,
    "montoDescuento": 0,
    "total": 705400,
    "estado": "Completo",
    "notas": "",
    "fechaEntregaEstimada": "2026-07-09",
    "fechaLimiteDespacho": "",
    "facturacionFE": 100,
    "facturacionRM": 0,
    "id": "ped_1783622197668",
    "numeroPedido": "ASYNC-SOP-1783622197668",
    "fecha": "2026-07-09",
    "campana": "Vacaciones 2026",
    "sincronizado": 0,
    "idLocal": 5
  }
]